usellm/__init__.py
usellm/use_llm.py
usellm/utils.py
usellm-0.0.7.dist-info/LICENSE
usellm-0.0.7.dist-info/METADATA
usellm-0.0.7.dist-info/WHEEL
usellm-0.0.7.dist-info/top_level.txt
usellm-0.0.7.dist-info/RECORD
