Metadata-Version: 2.1
Name: usellm
Version: 0.0.7
Summary: Use Large Language Models in Python App
Home-page: https://github.com/usellm/usellm-py
Author: Siddhant
Author-email: siddhant@jovian.com
License-File: LICENSE
Requires-Dist: requests (>=2.31.0)
